{
  "imagePath": "image-targets/elevator_risercard_luminance.png",
  "resources": {
    "originalImage": "elevator_risercard_original.png",
    "croppedImage": "elevator_risercard_cropped.png",
    "thumbnailImage": "elevator_risercard_thumbnail.png",
    "geometryImage": "elevator_risercard_geometry.png",
    "luminanceImage": "elevator_risercard_luminance.png"
  },
  "name": "elevator_risercard",
  "type": "PLANAR",
  "properties": {
    "top": 258,
    "left": 0,
    "width": 892,
    "height": 1189,
    "isRotated": true,
    "originalWidth": 892,
    "originalHeight": 1707
  },
  "userMetadataIsJson": true,
  "loadAutomatically": true,
  "created": 1761108021519,
  "updated": 1761108021519
}